LICENSE
MANIFEST.in
README.txt
setup.py
django_rsync/__init__.py
django_rsync/models.py
django_rsync/tests.py
django_rsync/views.py
django_rsync.egg-info/PKG-INFO
django_rsync.egg-info/SOURCES.txt
django_rsync.egg-info/dependency_links.txt
django_rsync.egg-info/top_level.txt
django_rsync/management/__init__.py
django_rsync/management/commands/__init__.py
django_rsync/management/commands/update_remote.py
docs/git_enabler_file