Metadata-Version: 1.1
Name: django-rsync
Version: 0.1
Summary: Simple deployment script using rsync for django projects
Home-page: https://github.com/hisie/django-rsync
Author: hisie
Author-email: dcebrian@serincas.com
License: Apache License, Version 2.0
Platform: UNKNOWN
Classifier: Environment :: Web Environment
Classifier: Framework :: Django
Classifier: Intended Audience :: Developers
Classifier: License :: OSI Approved :: Apache Software License
Classifier: Operating System :: OS Independent
Classifier: Programming Language :: Python
Classifier: Programming Language :: Python :: 2.6
Classifier: Programming Language :: Python :: 2.7
Classifier: Topic :: Internet :: WWW/HTTP
Classifier: Topic :: Internet :: WWW/HTTP :: Dynamic Content
